{
  "annotations": {
    "list": [
      {
        "1721hashKey": "object:165",
        "builtIn": 1,
        "datasource": "-- Grafana --",
        "enable": true,
        "hide": true,
        "iconColor": "rgba(0, 211, 255, 1)",
        "name": "Annotations & Alerts",
        "type": "dashboard"
      }
    ]
  },
  "editable": true,
  "gnetId": null,
  "graphTooltip": 0,
  "id": 7,
  "iteration": 1577089761398,
  "links": [],
  "panels": [
    {
      "collapsed": false,
      "datasource": null,
      "gridPos": {
        "h": 1,
        "w": 24,
        "x": 0,
        "y": 0
      },
      "id": 31,
      "panels": [],
      "title": "AWS Account Summary",
      "type": "row"
    },
    {
      "content": "### Account Name",
      "datasource": null,
      "gridPos": {
        "h": 2,
        "w": 3,
        "x": 0,
        "y": 1
      },
      "id": 8,
      "links": [],
      "mode": "markdown",
      "options": {},
      "repeat": null,
      "repeatDirection": null,
      "title": "",
      "transparent": true,
      "type": "text"
    },
    {
      "content": "### Month to date Spend",
      "datasource": null,
      "gridPos": {
        "h": 2,
        "w": 4,
        "x": 3,
        "y": 1
      },
      "id": 9,
      "links": [],
      "mode": "markdown",
      "options": {},
      "repeatDirection": "h",
      "title": "",
      "transparent": true,
      "type": "text"
    },
    {
      "content": "### Month Projected Spend",
      "datasource": null,
      "gridPos": {
        "h": 2,
        "w": 4,
        "x": 7,
        "y": 1
      },
      "id": 10,
      "links": [],
      "mode": "markdown",
      "options": {},
      "repeatDirection": "h",
      "title": "",
      "transparent": true,
      "type": "text"
    },
    {
      "content": "### Allocated Budget",
      "datasource": null,
      "gridPos": {
        "h": 2,
        "w": 4,
        "x": 11,
        "y": 1
      },
      "id": 11,
      "links": [],
      "mode": "markdown",
      "options": {},
      "repeatDirection": "h",
      "title": "",
      "transparent": true,
      "type": "text"
    },
    {
      "content": "### Percentage spend %",
      "datasource": null,
      "gridPos": {
        "h": 2,
        "w": 4,
        "x": 15,
        "y": 1
      },
      "id": 20,
      "links": [],
      "mode": "markdown",
      "options": {},
      "repeatDirection": "h",
      "title": "",
      "transparent": true,
      "type": "text"
    },
    {
      "content": "### Projected spend %",
      "datasource": null,
      "gridPos": {
        "h": 2,
        "w": 4,
        "x": 19,
        "y": 1
      },
      "id": 21,
      "links": [],
      "mode": "markdown",
      "options": {},
      "repeatDirection": "h",
      "title": "",
      "transparent": true,
      "type": "text"
    },
    {
      "cacheTimeout": null,
      "colorBackground": false,
      "colorPostfix": false,
      "colorValue": false,
      "colors": [
        "#299c46",
        "rgba(237, 129, 40, 0.89)",
        "#d44a3a"
      ],
      "datasource": "Prometheus",
      "format": "none",
      "gauge": {
        "maxValue": 100,
        "minValue": 0,
        "show": false,
        "thresholdLabels": false,
        "thresholdMarkers": true
      },
      "gridPos": {
        "h": 2,
        "w": 3,
        "x": 0,
        "y": 3
      },
      "id": 33,
      "interval": null,
      "links": [],
      "mappingType": 1,
      "mappingTypes": [
        {
          "name": "value to text",
          "value": 1
        },
        {
          "name": "range to text",
          "value": 2
        }
      ],
      "maxDataPoints": 100,
      "nullPointMode": "connected",
      "nullText": null,
      "options": {},
      "postfix": "",
      "postfixFontSize": "20%",
      "prefix": "",
      "prefixFontSize": "100%",
      "rangeMaps": [
        {
          "from": "null",
          "text": "N/A",
          "to": "null"
        }
      ],
      "repeat": "account_id",
      "repeatDirection": "v",
      "scopedVars": {
        "account_id": {
          "selected": false,
          "text": "937112502121",
          "value": "937112502121"
        }
      },
      "sparkline": {
        "fillColor": "rgba(31, 118, 189, 0.18)",
        "full": false,
        "lineColor": "rgb(31, 120, 193)",
        "show": false,
        "ymax": null,
        "ymin": null
      },
      "tableColumn": "",
      "targets": [
        {
          "expr": "aws_account_monthly_budget{account_id=~'$account_id', year='$year', month='$month'}",
          "format": "time_series",
          "instant": false,
          "legendFormat": "{{account_name}}",
          "refId": "A"
        }
      ],
      "thresholds": "",
      "title": "",
      "type": "singlestat",
      "valueFontSize": "50%",
      "valueMaps": [],
      "valueName": "name"
    },
    {
      "cacheTimeout": null,
      "colorBackground": false,
      "colorValue": false,
      "colors": [
        "#299c46",
        "rgba(237, 129, 40, 0.89)",
        "#d44a3a"
      ],
      "datasource": "Prometheus",
      "decimals": 2,
      "format": "currencyUSD",
      "gauge": {
        "maxValue": 100,
        "minValue": 0,
        "show": false,
        "thresholdLabels": false,
        "thresholdMarkers": true
      },
      "gridPos": {
        "h": 2,
        "w": 4,
        "x": 3,
        "y": 3
      },
      "id": 15,
      "interval": null,
      "links": [],
      "mappingType": 1,
      "mappingTypes": [
        {
          "name": "value to text",
          "value": 1
        },
        {
          "name": "range to text",
          "value": 2
        }
      ],
      "maxDataPoints": 100,
      "nullPointMode": "connected",
      "nullText": null,
      "options": {},
      "postfix": "",
      "postfixFontSize": "100%",
      "prefix": "",
      "prefixFontSize": "100%",
      "rangeMaps": [
        {
          "from": "null",
          "text": "N/A",
          "to": "null"
        }
      ],
      "repeat": "account_id",
      "repeatDirection": "v",
      "scopedVars": {
        "account_id": {
          "selected": false,
          "text": "937112502121",
          "value": "937112502121"
        }
      },
      "sparkline": {
        "fillColor": "rgba(31, 118, 189, 0.18)",
        "full": false,
        "lineColor": "rgb(31, 120, 193)",
        "show": false
      },
      "tableColumn": "",
      "targets": [
        {
          "expr": "sum(ce_aws_account_monthly_spend{account_id='$account_id', year='$year', month='$month'}) by (account_id) - (sum(ce_aws_account_monthly_spend{account_id='$account_id',year='$year', month='$month'}) by (account_id)/100 * $discount)",
          "format": "time_series",
          "hide": false,
          "intervalFactor": 1,
          "refId": "A"
        }
      ],
      "thresholds": "",
      "title": "",
      "type": "singlestat",
      "valueFontSize": "100%",
      "valueMaps": [
        {
          "op": "=",
          "text": "N/A",
          "value": "null"
        }
      ],
      "valueName": "current"
    },
    {
      "cacheTimeout": null,
      "colorBackground": false,
      "colorValue": false,
      "colors": [
        "#299c46",
        "rgba(237, 129, 40, 0.89)",
        "#d44a3a"
      ],
      "datasource": "Prometheus",
      "decimals": 2,
      "format": "currencyUSD",
      "gauge": {
        "maxValue": 100,
        "minValue": 0,
        "show": false,
        "thresholdLabels": false,
        "thresholdMarkers": true
      },
      "gridPos": {
        "h": 2,
        "w": 4,
        "x": 7,
        "y": 3
      },
      "id": 16,
      "interval": null,
      "links": [],
      "mappingType": 1,
      "mappingTypes": [
        {
          "name": "value to text",
          "value": 1
        },
        {
          "name": "range to text",
          "value": 2
        }
      ],
      "maxDataPoints": 100,
      "nullPointMode": "connected",
      "nullText": null,
      "options": {},
      "postfix": "",
      "postfixFontSize": "100%",
      "prefix": "",
      "prefixFontSize": "100%",
      "rangeMaps": [
        {
          "from": "null",
          "text": "N/A",
          "to": "null"
        }
      ],
      "repeat": "account_id",
      "repeatDirection": "v",
      "scopedVars": {
        "account_id": {
          "selected": false,
          "text": "937112502121",
          "value": "937112502121"
        }
      },
      "sparkline": {
        "fillColor": "rgba(31, 118, 189, 0.18)",
        "full": false,
        "lineColor": "rgb(31, 120, 193)",
        "show": false
      },
      "tableColumn": "",
      "targets": [
        {
          "expr": "sum(ce_aws_account_monthly_forecast{account_id='$account_id', year='$year', month='$month'}) by (account_id) - (sum(ce_aws_account_monthly_forecast{account_id='$account_id', year='$year', month='$month'}) by (account_id)/100 * $discount)",
          "format": "time_series",
          "hide": false,
          "intervalFactor": 1,
          "refId": "A"
        }
      ],
      "thresholds": "",
      "title": "",
      "type": "singlestat",
      "valueFontSize": "100%",
      "valueMaps": [
        {
          "op": "=",
          "text": "N/A",
          "value": "null"
        }
      ],
      "valueName": "current"
    },
    {
      "cacheTimeout": null,
      "colorBackground": false,
      "colorValue": false,
      "colors": [
        "#299c46",
        "rgba(237, 129, 40, 0.89)",
        "#d44a3a"
      ],
      "datasource": "Prometheus",
      "decimals": 2,
      "format": "currencyUSD",
      "gauge": {
        "maxValue": 100,
        "minValue": 0,
        "show": false,
        "thresholdLabels": false,
        "thresholdMarkers": true
      },
      "gridPos": {
        "h": 2,
        "w": 4,
        "x": 11,
        "y": 3
      },
      "hideTimeOverride": false,
      "id": 17,
      "interval": null,
      "links": [],
      "mappingType": 1,
      "mappingTypes": [
        {
          "name": "value to text",
          "value": 1
        },
        {
          "name": "range to text",
          "value": 2
        }
      ],
      "maxDataPoints": 100,
      "maxPerRow": 2,
      "nullPointMode": "connected",
      "nullText": null,
      "options": {},
      "postfix": "",
      "postfixFontSize": "100%",
      "prefix": "",
      "prefixFontSize": "100%",
      "rangeMaps": [
        {
          "from": "null",
          "text": "N/A",
          "to": "null"
        }
      ],
      "repeat": "account_id",
      "repeatDirection": "v",
      "scopedVars": {
        "account_id": {
          "selected": false,
          "text": "937112502121",
          "value": "937112502121"
        }
      },
      "sparkline": {
        "fillColor": "rgba(31, 118, 189, 0.18)",
        "full": false,
        "lineColor": "rgb(31, 120, 193)",
        "show": false
      },
      "tableColumn": "",
      "targets": [
        {
          "expr": "sum(aws_account_monthly_budget{account_id='$account_id', year='$year', month='$month'}) by (account_id, month, year)",
          "format": "time_series",
          "hide": false,
          "instant": false,
          "intervalFactor": 1,
          "refId": "A"
        }
      ],
      "thresholds": "",
      "title": "",
      "type": "singlestat",
      "valueFontSize": "100%",
      "valueMaps": [
        {
          "op": "=",
          "text": "N/A",
          "value": "null"
        }
      ],
      "valueName": "current"
    },
    {
      "cacheTimeout": null,
      "colorBackground": true,
      "colorValue": false,
      "colors": [
        "#629e51",
        "rgba(237, 129, 40, 0.89)",
        "#d44a3a"
      ],
      "datasource": "Prometheus",
      "decimals": 2,
      "format": "percent",
      "gauge": {
        "maxValue": 100,
        "minValue": 0,
        "show": false,
        "thresholdLabels": false,
        "thresholdMarkers": true
      },
      "gridPos": {
        "h": 2,
        "w": 4,
        "x": 15,
        "y": 3
      },
      "id": 25,
      "interval": null,
      "links": [],
      "mappingType": 1,
      "mappingTypes": [
        {
          "name": "value to text",
          "value": 1
        },
        {
          "name": "range to text",
          "value": 2
        }
      ],
      "maxDataPoints": 100,
      "nullPointMode": "connected",
      "nullText": null,
      "options": {},
      "postfix": "",
      "postfixFontSize": "100%",
      "prefix": "",
      "prefixFontSize": "100%",
      "rangeMaps": [
        {
          "from": "null",
          "text": "N/A",
          "to": "null"
        }
      ],
      "repeat": "account_id",
      "repeatDirection": "v",
      "scopedVars": {
        "account_id": {
          "selected": false,
          "text": "937112502121",
          "value": "937112502121"
        }
      },
      "sparkline": {
        "fillColor": "rgba(31, 118, 189, 0.18)",
        "full": false,
        "lineColor": "rgb(31, 120, 193)",
        "show": false
      },
      "tableColumn": "",
      "targets": [
        {
          "expr": "((sum(ce_aws_account_monthly_spend{account_id='$account_id',year='$year', month='$month' }) by (account_id)  - (sum(ce_aws_account_monthly_spend{account_id='$account_id',year='$year', month='$month'}) by (account_id)/100 * $discount)) / sum(aws_account_monthly_budget{account_id='$account_id',year='$year', month='$month'}) by (account_id)) * 100",
          "format": "time_series",
          "hide": false,
          "intervalFactor": 1,
          "refId": "A",
          "target": ""
        }
      ],
      "thresholds": "90,100",
      "title": "",
      "type": "singlestat",
      "valueFontSize": "100%",
      "valueMaps": [
        {
          "op": "=",
          "text": "N/A",
          "value": "null"
        }
      ],
      "valueName": "current"
    },
    {
      "cacheTimeout": null,
      "colorBackground": true,
      "colorValue": false,
      "colors": [
        "#629e51",
        "rgba(237, 129, 40, 0.89)",
        "#d44a3a"
      ],
      "datasource": "Prometheus",
      "decimals": 2,
      "format": "percent",
      "gauge": {
        "maxValue": 100,
        "minValue": 0,
        "show": false,
        "thresholdLabels": false,
        "thresholdMarkers": true
      },
      "gridPos": {
        "h": 2,
        "w": 4,
        "x": 19,
        "y": 3
      },
      "id": 26,
      "interval": null,
      "links": [],
      "mappingType": 1,
      "mappingTypes": [
        {
          "name": "value to text",
          "value": 1
        },
        {
          "name": "range to text",
          "value": 2
        }
      ],
      "maxDataPoints": 100,
      "nullPointMode": "connected",
      "nullText": null,
      "options": {},
      "postfix": "",
      "postfixFontSize": "100%",
      "prefix": "",
      "prefixFontSize": "100%",
      "rangeMaps": [
        {
          "from": "null",
          "text": "N/A",
          "to": "null"
        }
      ],
      "repeat": "account_id",
      "repeatDirection": "v",
      "scopedVars": {
        "account_id": {
          "selected": false,
          "text": "937112502121",
          "value": "937112502121"
        }
      },
      "sparkline": {
        "fillColor": "rgba(31, 118, 189, 0.18)",
        "full": false,
        "lineColor": "rgb(31, 120, 193)",
        "show": false
      },
      "tableColumn": "",
      "targets": [
        {
          "expr": "((sum(ce_aws_account_monthly_forecast{account_id='$account_id',year='$year', month='$month' }) by (account_id)  - (sum(ce_aws_account_monthly_forecast{account_id='$account_id',year='$year', month='$month'}) by (account_id)/100 * $discount)) / sum(aws_account_monthly_budget{account_id='$account_id',year='$year', month='$month'}) by (account_id)) * 100",
          "format": "time_series",
          "hide": false,
          "intervalFactor": 1,
          "refId": "A",
          "target": ""
        }
      ],
      "thresholds": "90,100",
      "title": "",
      "type": "singlestat",
      "valueFontSize": "100%",
      "valueMaps": [
        {
          "op": "=",
          "text": "N/A",
          "value": "null"
        }
      ],
      "valueName": "current"
    },
    {
      "collapsed": false,
      "datasource": null,
      "gridPos": {
        "h": 1,
        "w": 24,
        "x": 0,
        "y": 5
      },
      "id": 6,
      "panels": [],
      "repeat": "Account",
      "title": "AWS Service Summary",
      "type": "row"
    },
    {
      "aliasColors": {},
      "bars": true,
      "dashLength": 10,
      "dashes": false,
      "datasource": "Prometheus",
      "decimals": 2,
      "fill": 4,
      "fillGradient": 0,
      "gridPos": {
        "h": 11,
        "w": 11,
        "x": 0,
        "y": 6
      },
      "hiddenSeries": false,
      "id": 29,
      "legend": {
        "alignAsTable": true,
        "avg": false,
        "current": true,
        "hideEmpty": true,
        "hideZero": false,
        "max": false,
        "min": false,
        "rightSide": true,
        "show": true,
        "sideWidth": null,
        "sort": "current",
        "sortDesc": true,
        "total": false,
        "values": true
      },
      "lines": false,
      "linewidth": 3,
      "links": [],
      "nullPointMode": "null",
      "options": {
        "dataLinks": []
      },
      "percentage": true,
      "pointradius": 5,
      "points": true,
      "renderer": "flot",
      "repeatDirection": "v",
      "seriesOverrides": [],
      "spaceLength": 10,
      "stack": false,
      "steppedLine": false,
      "targets": [
        {
          "expr": "sum(ce_aws_service_daily_spend{account_id=~'$account_id', month='$month', year='$year'}) by (aws_service)  -\n(sum(ce_aws_service_daily_spend{account_id=~'$account_id', year='$year', month='$month'}) by (aws_service)/100 * $discount)",
          "format": "time_series",
          "hide": false,
          "intervalFactor": 1,
          "legendFormat": "{{aws_service}}",
          "refId": "A"
        }
      ],
      "thresholds": [],
      "timeFrom": null,
      "timeRegions": [],
      "timeShift": null,
      "title": "AWS Service Current Daily Spend",
      "tooltip": {
        "shared": false,
        "sort": 1,
        "value_type": "cumulative"
      },
      "type": "graph",
      "xaxis": {
        "buckets": null,
        "mode": "series",
        "name": null,
        "show": false,
        "values": [
          "current"
        ]
      },
      "yaxes": [
        {
          "decimals": 2,
          "format": "currencyUSD",
          "label": "Dollar($)",
          "logBase": 1,
          "max": null,
          "min": null,
          "show": true
        },
        {
          "format": "short",
          "label": null,
          "logBase": 1,
          "max": null,
          "min": null,
          "show": false
        }
      ],
      "yaxis": {
        "align": false,
        "alignLevel": null
      }
    },
    {
      "aliasColors": {},
      "bars": true,
      "dashLength": 10,
      "dashes": false,
      "datasource": "Prometheus",
      "decimals": 2,
      "fill": 1,
      "fillGradient": 0,
      "gridPos": {
        "h": 11,
        "w": 13,
        "x": 11,
        "y": 6
      },
      "hiddenSeries": false,
      "id": 32,
      "legend": {
        "alignAsTable": true,
        "avg": false,
        "current": true,
        "hideEmpty": false,
        "hideZero": false,
        "max": false,
        "min": false,
        "rightSide": true,
        "show": true,
        "sideWidth": null,
        "sort": "current",
        "sortDesc": true,
        "total": false,
        "values": true
      },
      "lines": false,
      "linewidth": 1,
      "links": [],
      "nullPointMode": "connected",
      "options": {
        "dataLinks": []
      },
      "percentage": true,
      "pointradius": 5,
      "points": false,
      "renderer": "flot",
      "repeatDirection": "h",
      "seriesOverrides": [],
      "spaceLength": 10,
      "stack": false,
      "steppedLine": false,
      "targets": [
        {
          "expr": "sum(ce_aws_service_monthly_spend{account_id=~'$account_id', month='$month', year='$year'}) by (aws_service) - (sum(ce_aws_service_monthly_spend{account_id=~'$account_id', year='$year', month='$month'}) by (aws_service)/100 * $discount)",
          "format": "time_series",
          "hide": false,
          "instant": false,
          "intervalFactor": 1,
          "legendFormat": "{{aws_service}}",
          "refId": "A"
        }
      ],
      "thresholds": [],
      "timeFrom": null,
      "timeRegions": [],
      "timeShift": null,
      "title": "AWS Service Monthly Cost Spend",
      "tooltip": {
        "shared": false,
        "sort": 1,
        "value_type": "cumulative"
      },
      "type": "graph",
      "xaxis": {
        "buckets": null,
        "mode": "series",
        "name": null,
        "show": false,
        "values": [
          "current"
        ]
      },
      "yaxes": [
        {
          "decimals": 2,
          "format": "currencyUSD",
          "label": "Dollar($)",
          "logBase": 1,
          "max": null,
          "min": null,
          "show": true
        },
        {
          "format": "short",
          "label": null,
          "logBase": 1,
          "max": null,
          "min": null,
          "show": false
        }
      ],
      "yaxis": {
        "align": false,
        "alignLevel": null
      }
    },
    {
      "aliasColors": {},
      "bars": true,
      "dashLength": 10,
      "dashes": false,
      "datasource": "Prometheus",
      "decimals": 2,
      "fill": 1,
      "fillGradient": 0,
      "gridPos": {
        "h": 8,
        "w": 24,
        "x": 0,
        "y": 17
      },
      "hiddenSeries": false,
      "id": 28,
      "legend": {
        "alignAsTable": true,
        "avg": false,
        "current": true,
        "hideEmpty": false,
        "hideZero": false,
        "max": false,
        "min": false,
        "rightSide": false,
        "show": true,
        "sideWidth": null,
        "sort": "current",
        "sortDesc": true,
        "total": false,
        "values": true
      },
      "lines": false,
      "linewidth": 1,
      "links": [],
      "nullPointMode": "connected",
      "options": {
        "dataLinks": []
      },
      "percentage": true,
      "pointradius": 5,
      "points": false,
      "renderer": "flot",
      "repeat": null,
      "repeatDirection": "h",
      "seriesOverrides": [],
      "spaceLength": 10,
      "stack": false,
      "steppedLine": false,
      "targets": [
        {
          "expr": "sum(ce_aws_service_monthly_forecast{account_id=~'$account_id', month='$month', year='$year'}) by (aws_service) - (sum(ce_aws_service_monthly_forecast{account_id=~'$account_id', year='$year', month='$month'}) by (aws_service)/100 * $discount)",
          "format": "time_series",
          "hide": false,
          "instant": false,
          "intervalFactor": 1,
          "legendFormat": "{{aws_service}}",
          "refId": "A"
        }
      ],
      "thresholds": [],
      "timeFrom": null,
      "timeRegions": [],
      "timeShift": null,
      "title": "AWS Service Monthly Projected Spend",
      "tooltip": {
        "shared": false,
        "sort": 1,
        "value_type": "cumulative"
      },
      "type": "graph",
      "xaxis": {
        "buckets": null,
        "mode": "series",
        "name": null,
        "show": false,
        "values": [
          "current"
        ]
      },
      "yaxes": [
        {
          "decimals": 2,
          "format": "currencyUSD",
          "label": "Dollar($)",
          "logBase": 1,
          "max": null,
          "min": null,
          "show": true
        },
        {
          "format": "short",
          "label": null,
          "logBase": 1,
          "max": null,
          "min": null,
          "show": false
        }
      ],
      "yaxis": {
        "align": false,
        "alignLevel": null
      }
    }
  ],
  "refresh": "5s",
  "schemaVersion": 21,
  "style": "dark",
  "tags": [],
  "templating": {
    "list": [
      {
        "allValue": null,
        "current": {
          "text": "Sanooj",
          "value": "Sanooj"
        },
        "datasource": "Prometheus",
        "definition": "",
        "hide": 0,
        "includeAll": false,
        "label": "Owner",
        "multi": false,
        "name": "account_owner",
        "options": [],
        "query": "label_values(owner)",
        "refresh": 2,
        "regex": "",
        "skipUrlSync": false,
        "sort": 0,
        "tagValuesQuery": "",
        "tags": [],
        "tagsQuery": "",
        "type": "query",
        "useTags": false
      },
      {
        "allValue": ".*.",
        "current": {
          "selected": false,
          "text": "All",
          "value": "$__all"
        },
        "datasource": "Prometheus",
        "definition": "aws_account_monthly_budget{owner=\"$account_owner\"}",
        "hide": 0,
        "includeAll": true,
        "label": "Account ID",
        "multi": false,
        "name": "account_id",
        "options": [],
        "query": "aws_account_monthly_budget{owner=\"$account_owner\"}",
        "refresh": 2,
        "regex": ".*account_id=\"(.*)\".*account_name.*",
        "skipUrlSync": false,
        "sort": 0,
        "tagValuesQuery": "",
        "tags": [],
        "tagsQuery": "",
        "type": "query",
        "useTags": false
      },
      {
        "allValue": null,
        "current": {
          "text": "2019",
          "value": "2019"
        },
        "datasource": "Prometheus",
        "definition": "",
        "hide": 0,
        "includeAll": false,
        "label": "Year",
        "multi": false,
        "name": "year",
        "options": [],
        "query": "label_values(year)",
        "refresh": 2,
        "regex": "",
        "skipUrlSync": false,
        "sort": 0,
        "tagValuesQuery": "",
        "tags": [],
        "tagsQuery": "",
        "type": "query",
        "useTags": false
      },
      {
        "allValue": null,
        "current": {
          "text": "12",
          "value": "12"
        },
        "datasource": "Prometheus",
        "definition": "",
        "hide": 0,
        "includeAll": false,
        "label": "Month",
        "multi": false,
        "name": "month",
        "options": [],
        "query": "label_values(month)",
        "refresh": 2,
        "regex": "",
        "skipUrlSync": false,
        "sort": 0,
        "tagValuesQuery": "",
        "tags": [],
        "tagsQuery": "",
        "type": "query",
        "useTags": false
      },
      {
        "allValue": null,
        "current": {
          "selected": false,
          "tags": [],
          "text": "5",
          "value": "5"
        },
        "hide": 0,
        "includeAll": false,
        "label": "Discount(%)",
        "multi": false,
        "name": "discount",
        "options": [
          {
            "selected": true,
            "text": "0",
            "value": "0"
          },
          {
            "selected": false,
            "text": "5",
            "value": "5"
          },
          {
            "selected": false,
            "text": "10",
            "value": "10"
          },
          {
            "selected": false,
            "text": "15",
            "value": "15"
          },
          {
            "selected": false,
            "text": "20",
            "value": "20"
          },
          {
            "selected": false,
            "text": "25",
            "value": "25"
          },
          {
            "selected": false,
            "text": "30",
            "value": "30"
          }
        ],
        "query": "0,5,10,15,20,25,30",
        "skipUrlSync": false,
        "type": "custom"
      }
    ]
  },
  "time": {
    "from": "now-1h",
    "to": "now"
  },
  "timepicker": {
    "refresh_intervals": [
      "5s",
      "10s",
      "30s",
      "1m",
      "5m",
      "15m",
      "30m",
      "1h",
      "2h",
      "1d"
    ],
    "time_options": [
      "5m",
      "15m",
      "1h",
      "6h",
      "12h",
      "24h",
      "2d",
      "7d",
      "30d"
    ]
  },
  "timezone": "browser",
  "title": "CE AWS Account Usage Dashboard",
  "uid": "ceaccountusagedashboard",
  "version": 1
}
